{
  "_meta": {
    "status": "SUCCESS",
    "cached": true,
    "count": 1,
    "debug": {
      "ticket": {
        "ticket_id": "1013805315_zz_zz_d_publ_en_2_2025-10-08_2025-10-13_1_3",
        "created_at": 1758065395.0909,
        "loop": null,
        "snapped_at": 1758065395.1817,
        "snapshot_id": "1013805315_zz_zz_d_publ_en_2_2025-10-08_2025-10-13_1_3",
        "snapshot_ttl": 300,
        "executions": 2,
        "progress": 1,
        "save_errors": []
      }
    }
  },
  "data": {
    "meta": [],
    "geo": {
      "hs_id": "xkx8jeq4hbuy",
      "region_name": "Rasdhoo",
      "region_name_long": "Rasdhoo, Maldives",
      "region_type": "CITY",
      "region_id": 6227584,
      "country_iso": "MV",
      "country": "maldives",
      "localised_country": "Maldives",
      "center": [
        4.26655,
        72.99018
      ],
      "centroid": [
        4.2669,
        72.99018
      ],
      "polygon": [
        "4.254605,72.99124",
        "4.263035,72.987716",
        "4.268655,72.976446",
        "4.27849,72.994054",
        "4.265142,73.003917",
        "4.254605,72.99124"
      ],
      "radius": 1.54,
      "zoom": -1,
      "search_by_polygon": 1,
      "cluster": 0,
      "properties": 54,
      "radius_override": 5,
      "boundingbox": {
        "ne": [
          4.279,
          73.004
        ],
        "sw": [
          4.254,
          72.976
        ]
      },
      "airports": [
        "MLE",
        "DRV"
      ],
      "region_name_en": "Rasdhoo",
      "region_name_long_en": "Rasdhoo, Maldives",
      "referrer_city_name_en": "Rasdhoo",
      "parent_region_id": 109,
      "parent_hs_id": "xmmmamtksdxx",
      "parent_region_name": "Maldives",
      "parent_region_name_long": "Maldives",
      "dynamic_bbox": {
        "ne": [
          4.262,
          72.992
        ],
        "sw": [
          4.262,
          72.992
        ]
      }
    },
    "records": [
      {
        "hs_id": 1013805315,
        "slug": "brickwood-ganduvaru-rasdhoo-mv-1013805315",
        "name": "Brickwood Ganduvaru",
        "toa": "bed_and_breakfast",
        "location": {
          "city": "Rasdhoo",
          "zip": "09020",
          "country_iso2": "MV",
          "address": "Huraangadu Hingun",
          "geoid": "xkx8jeq4hbuy",
          "loc": {
            "type": "Point"
          },
          "coordinates": {
            "lng": 72.992461,
            "lat": 4.262236
          }
        },
        "opening_time": {
          "check_in_from": "14:00",
          "check_in_to": null,
          "check_out_from": null,
          "check_out_to": "11:00"
        },
        "quality": {
          "stars": 0,
          "stars_is_estimated": false,
          "review_source": ""
        },
        "covid_safe": false,
        "amenities": {
          "children": [
            "babysitter",
            "children_playground"
          ],
          "wellness": [
            "spa"
          ],
          "internet": [
            "wifi_lobby",
            "wifi_room"
          ],
          "transfer": [
            "shuttle_service"
          ],
          "food_drink": [
            "restaurant",
            "cafe",
            "bar",
            "beach_bar"
          ],
          "disability": [
            "wheelchair_accessible",
            "disability_facilities"
          ],
          "parking": [
            "parking"
          ],
          "outdoor": [
            "garden"
          ],
          "room": [
            "fan",
            "air_conditioning",
            "in_room_safe"
          ],
          "reception": [
            "24h_reception",
            "luggage_storage",
            "concierge",
            "laundry_facilities",
            "safety_deposit_box"
          ]
        },
        "descriptions": {
          "hotel": "Make yourself at home in one of the 5 air-conditioned guestrooms. Complimentary wireless internet access is available to keep you connected. Conveniences include a turndown service and blackout drapes/curtains, and housekeeping is provided daily.",
          "direction": "Located in Rasdhoo, Brickwood Ganduvaru is near the beach, a 4-minute walk from Rasdhoo Reef Dive Site and within a 5-minute drive of Ukulhas Beach. This beach guesthouse is 1.1 mi (1.8 km) from Madivaru Finolhu and 1.2 mi (2 km) from Adivaru Thila Dive Site.",
          "amenities": true,
          "other": "Take in the views from a garden and make use of amenities such as complimentary wireless internet access and concierge services. Additional features at this guesthouse include a picnic area and charcoal grills.",
          "localized": "Located in Rasdhoo, Brickwood Ganduvaru is near the beach, a 4-minute walk from Rasdhoo Reef Dive Site and within a 5-minute drive of Ukulhas Beach. This beach guesthouse is 1.1 mi (1.8 km) from Madivaru Finolhu and 1.2 mi (2 km) from Adivaru Thila Dive Site."
        },
        "short_description": "Bed and breakfast with parking, restaurant and beach bar",
        "offers": [
          {
            "price": 98.82,
            "brt": "p2d#",
            "rf": "p2d#",
            "brf": 9502848,
            "rt": 9502848,
            "vendor": "htls",
            "vendor_id_raw": "3661241536",
            "mota_code": null,
            "direct_offer": false,
            "offer_flags": [
              "Breakfast included",
              "Free cancellation",
              "Pay at the property"
            ],
            "jc_code": "",
            "ranking_index": 0.9824731835660798,
            "chain": "",
            "free_cancellation": true,
            "special": false,
            "room_name": "Deluxe room",
            "rooms": [
              {
                "name": "Deluxe room",
                "flags": []
              }
            ],
            "offer_flags_new": {
              "breakfast": "Breakfast included",
              "refundable": "Free cancellation",
              "pay_at_hotel": "Pay at the property"
            },
            "partner_name": "Hotels.com",
            "partner_logo": "https://hotelscan.com/apis/vendors/htls/logo.svg?pos=zz"
          },
          {
            "vendor": "expd",
            "price": 94.49,
            "vendor_id_raw": "114382548",
            "mota_code": null,
            "jc_code": "EXPEDIA",
            "partner_name": "Expedia",
            "partner_logo": "https://hotelscan.com/apis/vendors/expd/logo.svg?pos=zz",
            "room_name": "Deluxe room",
            "brf": 9502784,
            "brt": "p2d#"
          }
        ],
        "all_offers": [
          {
            "price": 94.49,
            "brt": "p2d#",
            "rf": "p2d#",
            "brf": 9502784,
            "rt": 9502784,
            "vendor": "expd",
            "vendor_id_raw": "114382548",
            "mota_code": null,
            "direct_offer": false,
            "offer_flags": [
              "Breakfast included",
              "Free cancellation"
            ],
            "jc_code": "EXPEDIA",
            "chain": "",
            "free_cancellation": true,
            "special": false,
            "room_name": "Deluxe room",
            "rooms": [
              {
                "name": "Deluxe room",
                "flags": []
              }
            ],
            "offer_flags_new": {
              "breakfast": "Breakfast included",
              "refundable": "Free cancellation"
            },
            "partner_name": "Expedia",
            "partner_logo": "https://hotelscan.com/apis/vendors/expd/logo.svg?pos=zz"
          },
          {
            "price": 98.82,
            "brt": "p2d#",
            "rf": "p2d#",
            "brf": 9502848,
            "rt": 9502848,
            "vendor": "htls",
            "vendor_id_raw": "3661241536",
            "mota_code": null,
            "direct_offer": false,
            "offer_flags": [
              "Breakfast included",
              "Free cancellation",
              "Pay at the property"
            ],
            "jc_code": "",
            "chain": "",
            "free_cancellation": true,
            "special": false,
            "room_name": "Deluxe room",
            "rooms": [
              {
                "name": "Deluxe room",
                "flags": []
              }
            ],
            "offer_flags_new": {
              "breakfast": "Breakfast included",
              "refundable": "Free cancellation",
              "pay_at_hotel": "Pay at the property"
            },
            "partner_name": "Hotels.com",
            "partner_logo": "https://hotelscan.com/apis/vendors/htls/logo.svg?pos=zz"
          },
          {
            "price": 98.82,
            "brt": "p2d#",
            "rf": "p2d#",
            "brf": 9502848,
            "rt": 9502848,
            "vendor": "expd",
            "vendor_id_raw": "114382548",
            "mota_code": null,
            "direct_offer": false,
            "offer_flags": [
              "Breakfast included",
              "Free cancellation",
              "Pay at the property"
            ],
            "jc_code": "EXPEDIA",
            "chain": "",
            "free_cancellation": true,
            "special": false,
            "room_name": "Deluxe room",
            "rooms": [
              {
                "name": "Deluxe room",
                "flags": []
              }
            ],
            "offer_flags_new": {
              "breakfast": "Breakfast included",
              "refundable": "Free cancellation",
              "pay_at_hotel": "Pay at the property"
            },
            "partner_name": "Expedia",
            "partner_logo": "https://hotelscan.com/apis/vendors/expd/logo.svg?pos=zz"
          },
          {
            "price": 98.83,
            "brt": "p2d#",
            "rf": "p2d#",
            "brf": 9502784,
            "rt": 9502784,
            "vendor": "htls",
            "vendor_id_raw": "3661241536",
            "mota_code": null,
            "direct_offer": false,
            "offer_flags": [
              "Breakfast included",
              "Free cancellation"
            ],
            "jc_code": "",
            "chain": "",
            "free_cancellation": true,
            "special": false,
            "room_name": "Deluxe room",
            "rooms": [
              {
                "name": "Deluxe room",
                "flags": []
              }
            ],
            "offer_flags_new": {
              "breakfast": "Breakfast included",
              "refundable": "Free cancellation"
            },
            "partner_name": "Hotels.com",
            "partner_logo": "https://hotelscan.com/apis/vendors/htls/logo.svg?pos=zz"
          },
          {
            "price": 116.37,
            "brt": "p2d#",
            "rf": "p2d#",
            "brf": 9502784,
            "rt": 9502784,
            "vendor": "expd",
            "vendor_id_raw": "114382548",
            "mota_code": null,
            "direct_offer": false,
            "offer_flags": [
              "Breakfast included",
              "Free cancellation"
            ],
            "jc_code": "EXPEDIA",
            "chain": "",
            "free_cancellation": true,
            "special": false,
            "room_name": "Deluxe room",
            "rooms": [
              {
                "name": "Deluxe room",
                "flags": []
              }
            ],
            "offer_flags_new": {
              "breakfast": "Breakfast included",
              "refundable": "Free cancellation"
            },
            "partner_name": "Expedia",
            "partner_logo": "https://hotelscan.com/apis/vendors/expd/logo.svg?pos=zz"
          },
          {
            "price": 122.45,
            "brt": "p2d#",
            "rf": "p2d#",
            "brf": 9502848,
            "rt": 9502848,
            "vendor": "htls",
            "vendor_id_raw": "3661241536",
            "mota_code": null,
            "direct_offer": false,
            "offer_flags": [
              "Breakfast included",
              "Free cancellation",
              "Pay at the property"
            ],
            "jc_code": "",
            "chain": "",
            "free_cancellation": true,
            "special": false,
            "room_name": "Deluxe room",
            "rooms": [
              {
                "name": "Deluxe room",
                "flags": []
              }
            ],
            "offer_flags_new": {
              "breakfast": "Breakfast included",
              "refundable": "Free cancellation",
              "pay_at_hotel": "Pay at the property"
            },
            "partner_name": "Hotels.com",
            "partner_logo": "https://hotelscan.com/apis/vendors/htls/logo.svg?pos=zz"
          },
          {
            "price": 122.45,
            "brt": "p2d#",
            "rf": "p2d#",
            "brf": 9502848,
            "rt": 9502848,
            "vendor": "expd",
            "vendor_id_raw": "114382548",
            "mota_code": null,
            "direct_offer": false,
            "offer_flags": [
              "Breakfast included",
              "Free cancellation",
              "Pay at the property"
            ],
            "jc_code": "EXPEDIA",
            "chain": "",
            "free_cancellation": true,
            "special": false,
            "room_name": "Deluxe room",
            "rooms": [
              {
                "name": "Deluxe room",
                "flags": []
              }
            ],
            "offer_flags_new": {
              "breakfast": "Breakfast included",
              "refundable": "Free cancellation",
              "pay_at_hotel": "Pay at the property"
            },
            "partner_name": "Expedia",
            "partner_logo": "https://hotelscan.com/apis/vendors/expd/logo.svg?pos=zz"
          },
          {
            "price": 122.46,
            "brt": "p2d#",
            "rf": "p2d#",
            "brf": 9502784,
            "rt": 9502784,
            "vendor": "htls",
            "vendor_id_raw": "3661241536",
            "mota_code": null,
            "direct_offer": false,
            "offer_flags": [
              "Breakfast included",
              "Free cancellation"
            ],
            "jc_code": "",
            "chain": "",
            "free_cancellation": true,
            "special": false,
            "room_name": "Deluxe room",
            "rooms": [
              {
                "name": "Deluxe room",
                "flags": []
              }
            ],
            "offer_flags_new": {
              "breakfast": "Breakfast included",
              "refundable": "Free cancellation"
            },
            "partner_name": "Hotels.com",
            "partner_logo": "https://hotelscan.com/apis/vendors/htls/logo.svg?pos=zz"
          },
          {
            "price": 178.14,
            "brt": "f2c#",
            "rf": "f2c#",
            "brf": 8454720,
            "rt": 8454720,
            "vendor": "expd",
            "vendor_id_raw": "114382548",
            "mota_code": null,
            "direct_offer": false,
            "offer_flags": [
              "Free cancellation",
              "Garden view"
            ],
            "jc_code": "EXPEDIA",
            "chain": "",
            "free_cancellation": true,
            "special": false,
            "room_name": "Superior apartment",
            "rooms": [
              {
                "name": "Superior apartment",
                "flags": []
              }
            ],
            "offer_flags_new": {
              "refundable": "Free cancellation",
              "view_garden": "Garden view"
            },
            "partner_name": "Expedia",
            "partner_logo": "https://hotelscan.com/apis/vendors/expd/logo.svg?pos=zz"
          },
          {
            "price": 187.15,
            "brt": "f2c#",
            "rf": "f2c#",
            "brf": 9503296,
            "rt": 9503296,
            "vendor": "expd",
            "vendor_id_raw": "114382548",
            "mota_code": null,
            "direct_offer": false,
            "offer_flags": [
              "Breakfast included",
              "Free cancellation",
              "Garden view"
            ],
            "jc_code": "EXPEDIA",
            "chain": "",
            "free_cancellation": true,
            "special": false,
            "room_name": "Superior apartment",
            "rooms": [
              {
                "name": "Superior apartment",
                "flags": []
              }
            ],
            "offer_flags_new": {
              "breakfast": "Breakfast included",
              "refundable": "Free cancellation",
              "view_garden": "Garden view"
            },
            "partner_name": "Expedia",
            "partner_logo": "https://hotelscan.com/apis/vendors/expd/logo.svg?pos=zz"
          },
          {
            "price": 187.44,
            "brt": "f2c#",
            "rf": "f2c#",
            "brf": 8454784,
            "rt": 8454784,
            "vendor": "htls",
            "vendor_id_raw": "3661241536",
            "mota_code": null,
            "direct_offer": false,
            "offer_flags": [
              "Free cancellation",
              "Garden view",
              "Pay at the property"
            ],
            "jc_code": "",
            "chain": "",
            "free_cancellation": true,
            "special": false,
            "room_name": "Superior apartment",
            "rooms": [
              {
                "name": "Superior apartment",
                "flags": []
              }
            ],
            "offer_flags_new": {
              "refundable": "Free cancellation",
              "view_garden": "Garden view",
              "pay_at_hotel": "Pay at the property"
            },
            "partner_name": "Hotels.com",
            "partner_logo": "https://hotelscan.com/apis/vendors/htls/logo.svg?pos=zz"
          },
          {
            "price": 187.44,
            "brt": "f2c#",
            "rf": "f2c#",
            "brf": 8454784,
            "rt": 8454784,
            "vendor": "expd",
            "vendor_id_raw": "114382548",
            "mota_code": null,
            "direct_offer": false,
            "offer_flags": [
              "Free cancellation",
              "Garden view",
              "Pay at the property"
            ],
            "jc_code": "EXPEDIA",
            "chain": "",
            "free_cancellation": true,
            "special": false,
            "room_name": "Superior apartment",
            "rooms": [
              {
                "name": "Superior apartment",
                "flags": []
              }
            ],
            "offer_flags_new": {
              "refundable": "Free cancellation",
              "view_garden": "Garden view",
              "pay_at_hotel": "Pay at the property"
            },
            "partner_name": "Expedia",
            "partner_logo": "https://hotelscan.com/apis/vendors/expd/logo.svg?pos=zz"
          },
          {
            "price": 197.29,
            "brt": "f2c#",
            "rf": "f2c#",
            "brf": 9503360,
            "rt": 9503360,
            "vendor": "htls",
            "vendor_id_raw": "3661241536",
            "mota_code": null,
            "direct_offer": false,
            "offer_flags": [
              "Breakfast included",
              "Free cancellation",
              "Garden view",
              "Pay at the property"
            ],
            "jc_code": "",
            "chain": "",
            "free_cancellation": true,
            "special": false,
            "room_name": "Superior apartment",
            "rooms": [
              {
                "name": "Superior apartment",
                "flags": []
              }
            ],
            "offer_flags_new": {
              "breakfast": "Breakfast included",
              "refundable": "Free cancellation",
              "view_garden": "Garden view",
              "pay_at_hotel": "Pay at the property"
            },
            "partner_name": "Hotels.com",
            "partner_logo": "https://hotelscan.com/apis/vendors/htls/logo.svg?pos=zz"
          },
          {
            "price": 197.29,
            "brt": "f2c#",
            "rf": "f2c#",
            "brf": 9503360,
            "rt": 9503360,
            "vendor": "expd",
            "vendor_id_raw": "114382548",
            "mota_code": null,
            "direct_offer": false,
            "offer_flags": [
              "Breakfast included",
              "Free cancellation",
              "Garden view",
              "Pay at the property"
            ],
            "jc_code": "EXPEDIA",
            "chain": "",
            "free_cancellation": true,
            "special": false,
            "room_name": "Superior apartment",
            "rooms": [
              {
                "name": "Superior apartment",
                "flags": []
              }
            ],
            "offer_flags_new": {
              "breakfast": "Breakfast included",
              "refundable": "Free cancellation",
              "view_garden": "Garden view",
              "pay_at_hotel": "Pay at the property"
            },
            "partner_name": "Expedia",
            "partner_logo": "https://hotelscan.com/apis/vendors/expd/logo.svg?pos=zz"
          },
          {
            "price": 210.31,
            "brt": "f2c#",
            "rf": "f2c#",
            "brf": 9503296,
            "rt": 9503296,
            "vendor": "expd",
            "vendor_id_raw": "114382548",
            "mota_code": null,
            "direct_offer": false,
            "offer_flags": [
              "Breakfast included",
              "Free cancellation",
              "Garden view"
            ],
            "jc_code": "EXPEDIA",
            "chain": "",
            "free_cancellation": true,
            "special": false,
            "room_name": "Superior apartment",
            "rooms": [
              {
                "name": "Superior apartment",
                "flags": []
              }
            ],
            "offer_flags_new": {
              "breakfast": "Breakfast included",
              "refundable": "Free cancellation",
              "view_garden": "Garden view"
            },
            "partner_name": "Expedia",
            "partner_logo": "https://hotelscan.com/apis/vendors/expd/logo.svg?pos=zz"
          },
          {
            "price": 220.92,
            "brt": "f2c#",
            "rf": "f2c#",
            "brf": 9503360,
            "rt": 9503360,
            "vendor": "htls",
            "vendor_id_raw": "3661241536",
            "mota_code": null,
            "direct_offer": false,
            "offer_flags": [
              "Breakfast included",
              "Free cancellation",
              "Garden view",
              "Pay at the property"
            ],
            "jc_code": "",
            "chain": "",
            "free_cancellation": true,
            "special": false,
            "room_name": "Superior apartment",
            "rooms": [
              {
                "name": "Superior apartment",
                "flags": []
              }
            ],
            "offer_flags_new": {
              "breakfast": "Breakfast included",
              "refundable": "Free cancellation",
              "view_garden": "Garden view",
              "pay_at_hotel": "Pay at the property"
            },
            "partner_name": "Hotels.com",
            "partner_logo": "https://hotelscan.com/apis/vendors/htls/logo.svg?pos=zz"
          },
          {
            "price": 220.92,
            "brt": "f2c#",
            "rf": "f2c#",
            "brf": 9503360,
            "rt": 9503360,
            "vendor": "expd",
            "vendor_id_raw": "114382548",
            "mota_code": null,
            "direct_offer": false,
            "offer_flags": [
              "Breakfast included",
              "Free cancellation",
              "Garden view",
              "Pay at the property"
            ],
            "jc_code": "EXPEDIA",
            "chain": "",
            "free_cancellation": true,
            "special": false,
            "room_name": "Superior apartment",
            "rooms": [
              {
                "name": "Superior apartment",
                "flags": []
              }
            ],
            "offer_flags_new": {
              "breakfast": "Breakfast included",
              "refundable": "Free cancellation",
              "view_garden": "Garden view",
              "pay_at_hotel": "Pay at the property"
            },
            "partner_name": "Expedia",
            "partner_logo": "https://hotelscan.com/apis/vendors/expd/logo.svg?pos=zz"
          },
          {
            "price": 404.07,
            "brt": "p2d#",
            "rf": "p2d#",
            "brf": 9470016,
            "rt": 9470016,
            "vendor": "htls",
            "vendor_id_raw": "3240442976",
            "mota_code": null,
            "direct_offer": false,
            "offer_flags": [
              "Breakfast included"
            ],
            "jc_code": "",
            "chain": "",
            "free_cancellation": false,
            "special": false,
            "room_name": "Deluxe room",
            "rooms": [
              {
                "name": "Deluxe room",
                "flags": []
              }
            ],
            "offer_flags_new": {
              "breakfast": "Breakfast included"
            },
            "partner_name": "Hotels.com",
            "partner_logo": "https://hotelscan.com/apis/vendors/htls/logo.svg?pos=zz"
          },
          {
            "price": 404.07,
            "brt": "p2d#",
            "rf": "p2d#",
            "brf": 9470016,
            "rt": 9470016,
            "vendor": "expd",
            "vendor_id_raw": "101232593",
            "mota_code": null,
            "direct_offer": false,
            "offer_flags": [
              "Breakfast included"
            ],
            "jc_code": "EXPEDIA",
            "chain": "",
            "free_cancellation": false,
            "special": false,
            "room_name": "Deluxe room",
            "rooms": [
              {
                "name": "Deluxe room",
                "flags": []
              }
            ],
            "offer_flags_new": {
              "breakfast": "Breakfast included"
            },
            "partner_name": "Expedia",
            "partner_logo": "https://hotelscan.com/apis/vendors/expd/logo.svg?pos=zz"
          },
          {
            "price": 502.53,
            "brt": "f2q#",
            "rf": "f2q#",
            "brf": 9470016,
            "rt": 9470016,
            "vendor": "htls",
            "vendor_id_raw": "3240442976",
            "mota_code": null,
            "direct_offer": false,
            "offer_flags": [
              "Breakfast included"
            ],
            "jc_code": "",
            "chain": "",
            "free_cancellation": false,
            "special": false,
            "room_name": "Family apartment",
            "rooms": [
              {
                "name": "Family apartment",
                "flags": []
              }
            ],
            "offer_flags_new": {
              "breakfast": "Breakfast included"
            },
            "partner_name": "Hotels.com",
            "partner_logo": "https://hotelscan.com/apis/vendors/htls/logo.svg?pos=zz"
          },
          {
            "price": 502.53,
            "brt": "f2q#",
            "rf": "f2q#",
            "brf": 9470016,
            "rt": 9470016,
            "vendor": "expd",
            "vendor_id_raw": "101232593",
            "mota_code": null,
            "direct_offer": false,
            "offer_flags": [
              "Breakfast included"
            ],
            "jc_code": "EXPEDIA",
            "chain": "",
            "free_cancellation": false,
            "special": false,
            "room_name": "Family apartment",
            "rooms": [
              {
                "name": "Family apartment",
                "flags": []
              }
            ],
            "offer_flags_new": {
              "breakfast": "Breakfast included"
            },
            "partner_name": "Expedia",
            "partner_logo": "https://hotelscan.com/apis/vendors/expd/logo.svg?pos=zz"
          }
        ],
        "descriptions_language": {
          "general": {
            "original_language": true,
            "text": "Located in Rasdhoo, Brickwood Ganduvaru is near the beach, a 4-minute walk from Rasdhoo Reef Dive Site and within a 5-minute drive of Ukulhas Beach. This beach guesthouse is 1.1 mi (1.8 km) from Madivaru Finolhu and 1.2 mi (2 km) from Adivaru Thila Dive Site."
          },
          "hotel": {
            "original_language": true,
            "text": "Make yourself at home in one of the 5 air-conditioned guestrooms. Complimentary wireless internet access is available to keep you connected. Conveniences include a turndown service and blackout drapes/curtains, and housekeeping is provided daily."
          },
          "other": {
            "original_language": true,
            "text": "Take in the views from a garden and make use of amenities such as complimentary wireless internet access and concierge services. Additional features at this guesthouse include a picnic area and charcoal grills."
          }
        },
        "chain_code": null,
        "bids": {
          "expd": "j23",
          "htls": "j23"
        },
        "worst_offer": null,
        "best_offer": 94.49,
        "best_offer_ota": "expd",
        "best_offer_mota": null,
        "discount": 0,
        "offers_count": 21,
        "coordinates": {
          "lat": 4.262236,
          "lng": 72.992461
        },
        "distance": 0.54,
        "neighborhood": null,
        "badge": null,
        "distances": [
          {
            "from": "center",
            "distance": 0.54,
            "time": 750,
            "means": "foot",
            "means_type": "foot"
          }
        ],
        "specs": {
          "bathrooms": null,
          "beds": null,
          "bedrooms": null,
          "guests": null,
          "square_meters": null
        },
        "toa_label": "bed and breakfast",
        "top_amenities": [
          "wifi_room",
          "restaurant",
          "bar",
          "parking",
          "air_conditioning"
        ],
        "transportations": {
          "airports": [],
          "trains": []
        },
        "images": [
          {
            "image_id": "579233160",
            "label": ""
          },
          {
            "image_id": "579233171",
            "label": ""
          },
          {
            "image_id": "579233176",
            "label": ""
          },
          {
            "image_id": "579233178",
            "label": ""
          },
          {
            "image_id": "579233169",
            "label": ""
          },
          {
            "image_id": "579233179",
            "label": ""
          },
          {
            "image_id": "579233174",
            "label": ""
          },
          {
            "image_id": "579233177",
            "label": ""
          },
          {
            "image_id": "579233188",
            "label": ""
          },
          {
            "image_id": "579233175",
            "label": ""
          },
          {
            "image_id": "579233167",
            "label": ""
          },
          {
            "image_id": "579233180",
            "label": ""
          },
          {
            "image_id": "579233186",
            "label": ""
          },
          {
            "image_id": "579233172",
            "label": ""
          },
          {
            "image_id": "579233182",
            "label": ""
          }
        ],
        "hero_offer": {
          "price": 98.82,
          "brt": "p2d#",
          "rf": "p2d#",
          "brf": 9502848,
          "rt": 9502848,
          "vendor": "htls",
          "vendor_id_raw": "3661241536",
          "mota_code": null,
          "direct_offer": false,
          "offer_flags": {
            "breakfast": "Breakfast included",
            "refundable": "Free cancellation",
            "pay_at_hotel": "Pay at the property"
          },
          "jc_code": "",
          "ranking_index": 0.9824731835660798,
          "chain": "",
          "free_cancellation": true,
          "special": false,
          "room_name": "Deluxe room",
          "rooms": [
            {
              "name": "Deluxe room",
              "flags": []
            }
          ],
          "partner_name": "Hotels.com",
          "partner_logo": "https://hotelscan.com/apis/vendors/htls/logo.svg?pos=zz"
        },
        "rank": 0,
        "ctrl_srt": "im a ctrl teapot",
        "test_srt": "im a test teapot"
      }
    ],
    "filters": [],
    "query": {
      "pos": "zz"
    }
  }
}