{
  "_meta": {
    "status": "SUCCESS",
    "cached": true,
    "count": 1,
    "debug": {
      "ticket": {
        "ticket_id": "690337860_zz_zz_d_publ_en_2_2025-10-08_2025-10-13_1_3",
        "created_at": 1758065373.4132,
        "loop": null,
        "snapped_at": 1758065375.8053,
        "snapshot_id": "690337860_zz_zz_d_publ_en_2_2025-10-08_2025-10-13_1_3",
        "snapshot_ttl": 300,
        "executions": 6,
        "progress": 1,
        "save_errors": []
      }
    }
  },
  "data": {
    "meta": [],
    "geo": {
      "hs_id": "x5vu1qq78r12",
      "region_name": "Huvahendhoo",
      "region_name_long": "Huvahendhoo, Maldives",
      "region_type": "CITY",
      "region_id": 6130742,
      "country_iso": "MV",
      "country": "maldives",
      "localised_country": "Maldives",
      "center": [
        3.65737,
        72.95473
      ],
      "centroid": [
        3.65737,
        72.95447
      ],
      "polygon": [
        "3.665957,72.944061",
        "3.648781,72.94406",
        "3.649464,72.9654",
        "3.665265,72.965407",
        "3.665957,72.944061"
      ],
      "radius": 1.5,
      "zoom": -1,
      "search_by_polygon": 0,
      "cluster": 0,
      "properties": 5,
      "radius_override": 5,
      "boundingbox": {
        "ne": [
          3.666,
          72.966
        ],
        "sw": [
          3.648,
          72.944
        ]
      },
      "airports": [
        "MLE",
        "DRV"
      ],
      "region_name_en": "Huvahendhoo",
      "region_name_long_en": "Huvahendhoo, Maldives",
      "referrer_city_name_en": "Huvahendhoo",
      "parent_region_id": 6051084,
      "parent_hs_id": "x5p4hmhw6iot",
      "parent_region_name": "Maldives (all)",
      "parent_region_name_long": "Maldives (all)",
      "dynamic_bbox": {
        "ne": [
          3.652,
          72.953
        ],
        "sw": [
          3.652,
          72.953
        ]
      }
    },
    "records": [
      {
        "hs_id": 690337860,
        "slug": "lily-beach-resort-and-spa-all-inclusive-huvahendhoo-mv-690337860",
        "name": "Lily Beach Resort And Spa - All Inclusive",
        "toa": "resort",
        "location": {
          "city": "Huvahendhoo",
          "zip": "20077",
          "country_iso2": "MV",
          "address": "Huvahendhoo,south Ari Atoll, Maldives",
          "geoid": "x5vu1qq78r12",
          "loc": {
            "type": "Point"
          },
          "coordinates": {
            "lng": 72.9537,
            "lat": 3.65285
          }
        },
        "opening_time": {
          "check_in_from": "14:00",
          "check_in_to": "16:00",
          "check_out_from": "06:30",
          "check_out_to": "12:00"
        },
        "quality": {
          "review_count": 389,
          "review_rating": 92,
          "stars": 5,
          "stars_is_estimated": false,
          "review_source": ""
        },
        "covid_safe": true,
        "amenities": {
          "wellness": [
            "indoor_pool",
            "massage",
            "solarium",
            "fitness_center",
            "sauna",
            "spa",
            "outdoor_pool",
            "turkish_bath"
          ],
          "sports": [
            "golf",
            "billiard",
            "yoga",
            "ping_pong",
            "tennis",
            "volley_beach_volley",
            "sub",
            "surf"
          ],
          "internet": [
            "wifi",
            "internet"
          ],
          "food_drink": [
            "restaurant",
            "room_service",
            "poolside_bar",
            "cafe",
            "bar",
            "snack_bar"
          ],
          "disability": [
            "wheelchair_accessible"
          ],
          "outdoor": [
            "garden",
            "terrace"
          ],
          "other": [
            "lift"
          ],
          "business": [
            "business_services"
          ],
          "children": [
            "babysitter",
            "children_playground"
          ],
          "entertainment": [
            "tv_lobby",
            "disco"
          ],
          "transfer": [
            "shuttle_service"
          ],
          "room": [
            "air_conditioning",
            "tv"
          ],
          "reception": [
            "24h_reception",
            "luggage_storage",
            "concierge",
            "laundry_service",
            "safety_deposit_box"
          ]
        },
        "descriptions": {
          "direction": "Located in Huvahendhoo, Lily Beach Resort & Spa - All Inclusive is on a private beach. Villingilivaru Island Pier and Dhangethi Port are worth checking out if an activity is on the agenda, while those wishing to experience the area's natural beauty can explore Ari Atoll and Bunbaru Public Beach. Take an opportunity to explore the area for water adventures such as windsurfing and other activities like whale-watching.",
          "general": "Lily Beach Resort & Spa at Huvahendhoo as a Luxury 'Platinum Plan' Resort is approximately 25 minutes flying from the Male’ International Airport. *Price shown does NOT include arrival and return transfer, but is compulsory to book online Sunhotels POS,together with the hotel reservation. You are required to book the appropriate transfer and supply all the required transfer information. Hotel booking is not regarded as confirmed until the transfer booking has been completed. The all-new Lily Beach Resort & Spa officially opened on the 28th of March 2009. The Hotel whit Platinum Plan offers: gym, water sports centre equipped with non-motorized activities and motorized sports such as fun-tube rides and exhilarating banana-boat rides, a flood-lit tennis court, table tennis, darts, billiards/pool, beach volleyball. Big game fishing, sunrise fishing, or on a snorkeling safari. In the Evening: Live music, traditional local music, group games, discos, night fishing, traditional cultural variety shows, and various beach games. Deluxe Water Villas (36 Villas) : Villa Size 126m², with a distance of 15-feet between each villa, these villas are aesthetically appointed with a single piece hand-crafted standalone bathtub with Jacuzzi and an additional 7 sq.mts Jacuzzi pool on the deck offering a fantastic view of the entire lagoon accessible by your private stairs. A combination of natural wood and white marble flooring, a 4 poster king-sized bed, an over-sized day bed, and 42” LCD flat screen. In case of choosing the option of \"all inclusive\": The All Inclusive-concept includes all meals (breakfast, lunch, dinner and snacks) and mealtime drinks such as soft drinks, beer, wine, water and alcoholic drinks, all of local brands. Drinks are served from morning until late evening (approx until 22.-24.00 hrs). Opening times vary between different hotels. In certain hotels the activities program is also included. Children 0-2 yrs pay aprox. 8 USD directly at the resorts. You are requested to indicate the estimated arrival time and flight number while making the booking. Address: at Huvahendhoo South-East Ari Atoll Maldives Note: Transfer has to be booked at the same time as the Hotel",
          "amenities": true,
          "localized": "Lily Beach Resort & Spa at Huvahendhoo as a Luxury 'Platinum Plan' Resort is approximately 25 minutes flying from the Male’ International Airport. *Price shown does NOT include arrival and return transfer, but is compulsory to book online Sunhotels POS,together with the hotel reservation. You are required to book the appropriate transfer and supply all the required transfer information. Hotel booking is not regarded as confirmed until the transfer booking has been completed. The all-new Lily Beach Resort & Spa officially opened on the 28th of March 2009. The Hotel whit Platinum Plan offers: gym, water sports centre equipped with non-motorized activities and motorized sports such as fun-tube rides and exhilarating banana-boat rides, a flood-lit tennis court, table tennis, darts, billiards/pool, beach volleyball. Big game fishing, sunrise fishing, or on a snorkeling safari. In the Evening: Live music, traditional local music, group games, discos, night fishing, traditional cultural variety shows, and various beach games. Deluxe Water Villas (36 Villas) : Villa Size 126m², with a distance of 15-feet between each villa, these villas are aesthetically appointed with a single piece hand-crafted standalone bathtub with Jacuzzi and an additional 7 sq.mts Jacuzzi pool on the deck offering a fantastic view of the entire lagoon accessible by your private stairs. A combination of natural wood and white marble flooring, a 4 poster king-sized bed, an over-sized day bed, and 42” LCD flat screen. In case of choosing the option of \"all inclusive\": The All Inclusive-concept includes all meals (breakfast, lunch, dinner and snacks) and mealtime drinks such as soft drinks, beer, wine, water and alcoholic drinks, all of local brands. Drinks are served from morning until late evening (approx until 22.-24.00 hrs). Opening times vary between different hotels. In certain hotels the activities program is also included. Children 0-2 yrs pay aprox. 8 USD directly at the resorts. You are requested to indicate the estimated arrival time and flight number while making the booking. Address: at Huvahendhoo South-East Ari Atoll Maldives Note: Transfer has to be booked at the same time as the Hotel"
        },
        "short_description": "Stylish resort with 125 rooms, shuttle service and poolside bar",
        "chain": "lily_hotels",
        "brand": "lily_hotels",
        "offers": [
          {
            "price": 603.6,
            "brt": "o2r#",
            "rf": "o2r#",
            "brf": 9502784,
            "rt": 9502784,
            "vendor": "agda",
            "vendor_id_raw": "41483",
            "mota_code": null,
            "direct_offer": false,
            "offer_flags": [
              "Breakfast included",
              "Free cancellation"
            ],
            "jc_code": "",
            "ranking_index": 0.96,
            "chain": "",
            "free_cancellation": true,
            "special": false,
            "room_name": "Villa",
            "rooms": [
              {
                "name": "Villa",
                "flags": []
              }
            ],
            "offer_flags_new": {
              "breakfast": "Breakfast included",
              "refundable": "Free cancellation"
            },
            "partner_name": "Agoda",
            "partner_logo": "https://hotelscan.com/apis/vendors/agda/logo.svg?pos=zz"
          },
          {
            "vendor": "htls",
            "price": 748.3,
            "vendor_id_raw": "469335",
            "mota_code": null,
            "jc_code": "",
            "partner_name": "Hotels.com",
            "partner_logo": "https://hotelscan.com/apis/vendors/htls/logo.svg?pos=zz",
            "room_name": "Villa",
            "brf": 9502848,
            "brt": "o2r#"
          },
          {
            "vendor": "bkng",
            "price": 835.58,
            "vendor_id_raw": "568007",
            "mota_code": null,
            "jc_code": "",
            "partner_name": "Booking.com",
            "partner_logo": "https://hotelscan.com/apis/vendors/bkng/logo.svg?pos=zz",
            "room_name": "Villa",
            "brf": 11075648,
            "brt": "o2r#"
          },
          {
            "vendor": "ctrp",
            "price": 741.79,
            "vendor_id_raw": "1573552",
            "mota_code": null,
            "jc_code": "TRIPCOM",
            "partner_name": "Trip.com",
            "partner_logo": "https://hotelscan.com/apis/vendors/ctrp/logo.svg?pos=zz",
            "room_name": "Villa",
            "brf": 9502848,
            "brt": "o2r#"
          },
          {
            "vendor": "expd",
            "price": 748.3,
            "vendor_id_raw": "8751436",
            "mota_code": null,
            "jc_code": "EXPEDIA",
            "partner_name": "Expedia",
            "partner_logo": "https://hotelscan.com/apis/vendors/expd/logo.svg?pos=zz",
            "room_name": "Villa",
            "brf": 9502848,
            "brt": "o2r#"
          },
          {
            "vendor": "ostr",
            "price": 676.84,
            "vendor_id_raw": "8120201",
            "mota_code": null,
            "jc_code": "",
            "partner_name": "Zenhotels",
            "partner_logo": "https://hotelscan.com/apis/vendors/ostr/logo.svg?pos=zz",
            "room_name": "Villa - Queen bed",
            "brf": 11075648,
            "brt": "o2r#q"
          },
          {
            "vendor": "stfl",
            "price": 883.63,
            "vendor_id_raw": "52202",
            "mota_code": null,
            "jc_code": "",
            "partner_name": "Stayforlong",
            "partner_logo": "https://hotelscan.com/apis/vendors/stfl/logo.svg?pos=zz",
            "room_name": "Villa - Choice of single or double beds",
            "brf": 9470016,
            "brt": "o2r#b"
          }
        ],
        "all_offers": [
          {
            "price": 603.6,
            "brt": "o2r#",
            "rf": "o2r#",
            "brf": 9502784,
            "rt": 9502784,
            "vendor": "agda",
            "vendor_id_raw": "41483",
            "mota_code": null,
            "direct_offer": false,
            "offer_flags": [
              "Breakfast included",
              "Free cancellation"
            ],
            "jc_code": "",
            "chain": "",
            "free_cancellation": true,
            "special": false,
            "room_name": "Villa",
            "rooms": [
              {
                "name": "Villa",
                "flags": []
              }
            ],
            "offer_flags_new": {
              "breakfast": "Breakfast included",
              "refundable": "Free cancellation"
            },
            "partner_name": "Agoda",
            "partner_logo": "https://hotelscan.com/apis/vendors/agda/logo.svg?pos=zz"
          },
          {
            "price": 653.16,
            "brt": "o2r#",
            "rf": "o2r#",
            "brf": 9502784,
            "rt": 9502784,
            "vendor": "agda",
            "vendor_id_raw": "41483",
            "mota_code": null,
            "direct_offer": false,
            "offer_flags": [
              "Breakfast included",
              "Free cancellation"
            ],
            "jc_code": "",
            "chain": "",
            "free_cancellation": true,
            "special": false,
            "room_name": "Villa",
            "rooms": [
              {
                "name": "Villa",
                "flags": []
              }
            ],
            "offer_flags_new": {
              "breakfast": "Breakfast included",
              "refundable": "Free cancellation"
            },
            "partner_name": "Agoda",
            "partner_logo": "https://hotelscan.com/apis/vendors/agda/logo.svg?pos=zz"
          },
          {
            "price": 676.84,
            "brt": "o2r#q",
            "rf": "o2r#q",
            "brf": 11075648,
            "rt": 11075648,
            "vendor": "ostr",
            "vendor_id_raw": "8120201",
            "mota_code": null,
            "direct_offer": false,
            "offer_flags": [
              "Free cancellation"
            ],
            "jc_code": "",
            "chain": "",
            "free_cancellation": true,
            "special": false,
            "room_name": "Villa - Queen bed",
            "rooms": [
              {
                "name": "Villa - Queen bed",
                "flags": [
                  "Queen bed"
                ]
              }
            ],
            "offer_flags_new": {
              "refundable": "Free cancellation"
            },
            "partner_name": "Zenhotels",
            "partner_logo": "https://hotelscan.com/apis/vendors/ostr/logo.svg?pos=zz"
          },
          {
            "price": 732.4,
            "brt": "o2r#k",
            "rf": "o2r#k",
            "brf": 11075648,
            "rt": 11075648,
            "vendor": "ostr",
            "vendor_id_raw": "8120201",
            "mota_code": null,
            "direct_offer": false,
            "offer_flags": [
              "Free cancellation"
            ],
            "jc_code": "",
            "chain": "",
            "free_cancellation": true,
            "special": false,
            "room_name": "Villa - King bed",
            "rooms": [
              {
                "name": "Villa - King bed",
                "flags": [
                  "King bed"
                ]
              }
            ],
            "offer_flags_new": {
              "refundable": "Free cancellation"
            },
            "partner_name": "Zenhotels",
            "partner_logo": "https://hotelscan.com/apis/vendors/ostr/logo.svg?pos=zz"
          },
          {
            "price": 741.62,
            "brt": "o2r#q",
            "rf": "o2r#q",
            "brf": 11075712,
            "rt": 11075712,
            "vendor": "ostr",
            "vendor_id_raw": "8120201",
            "mota_code": null,
            "direct_offer": false,
            "offer_flags": [
              "Free cancellation",
              "Pay at the property"
            ],
            "jc_code": "",
            "chain": "",
            "free_cancellation": true,
            "special": false,
            "room_name": "Villa - Queen bed",
            "rooms": [
              {
                "name": "Villa - Queen bed",
                "flags": [
                  "Queen bed"
                ]
              }
            ],
            "offer_flags_new": {
              "refundable": "Free cancellation",
              "pay_at_hotel": "Pay at the property"
            },
            "partner_name": "Zenhotels",
            "partner_logo": "https://hotelscan.com/apis/vendors/ostr/logo.svg?pos=zz"
          },
          {
            "price": 741.79,
            "brt": "o2r#",
            "rf": "o2r#",
            "brf": 9502848,
            "rt": 9502848,
            "vendor": "ctrp",
            "vendor_id_raw": "1573552",
            "mota_code": null,
            "direct_offer": false,
            "offer_flags": [
              "Breakfast included",
              "Free cancellation",
              "Pay at the property"
            ],
            "jc_code": "TRIPCOM",
            "chain": "",
            "free_cancellation": true,
            "special": false,
            "room_name": "Villa",
            "rooms": [
              {
                "name": "Villa",
                "flags": []
              }
            ],
            "offer_flags_new": {
              "breakfast": "Breakfast included",
              "refundable": "Free cancellation",
              "pay_at_hotel": "Pay at the property"
            },
            "partner_name": "Trip.com",
            "partner_logo": "https://hotelscan.com/apis/vendors/ctrp/logo.svg?pos=zz"
          },
          {
            "price": 748.3,
            "brt": "o2r#",
            "rf": "o2r#",
            "brf": 9502848,
            "rt": 9502848,
            "vendor": "htls",
            "vendor_id_raw": "469335",
            "mota_code": null,
            "direct_offer": false,
            "offer_flags": [
              "Breakfast included",
              "Free cancellation",
              "Pay at the property"
            ],
            "jc_code": "",
            "chain": "",
            "free_cancellation": true,
            "special": false,
            "room_name": "Villa",
            "rooms": [
              {
                "name": "Villa",
                "flags": []
              }
            ],
            "offer_flags_new": {
              "breakfast": "Breakfast included",
              "refundable": "Free cancellation",
              "pay_at_hotel": "Pay at the property"
            },
            "partner_name": "Hotels.com",
            "partner_logo": "https://hotelscan.com/apis/vendors/htls/logo.svg?pos=zz"
          },
          {
            "price": 748.3,
            "brt": "o2r#",
            "rf": "o2r#",
            "brf": 9502848,
            "rt": 9502848,
            "vendor": "expd",
            "vendor_id_raw": "8751436",
            "mota_code": null,
            "direct_offer": false,
            "offer_flags": [
              "Breakfast included",
              "Free cancellation",
              "Pay at the property"
            ],
            "jc_code": "EXPEDIA",
            "chain": "",
            "free_cancellation": true,
            "special": false,
            "room_name": "Villa",
            "rooms": [
              {
                "name": "Villa",
                "flags": []
              }
            ],
            "offer_flags_new": {
              "breakfast": "Breakfast included",
              "refundable": "Free cancellation",
              "pay_at_hotel": "Pay at the property"
            },
            "partner_name": "Expedia",
            "partner_logo": "https://hotelscan.com/apis/vendors/expd/logo.svg?pos=zz"
          },
          {
            "price": 749.01,
            "brt": "o2r#",
            "rf": "o2r#",
            "brf": 9502784,
            "rt": 9502784,
            "vendor": "ctrp",
            "vendor_id_raw": "1573552",
            "mota_code": null,
            "direct_offer": false,
            "offer_flags": [
              "Breakfast included",
              "Free cancellation"
            ],
            "jc_code": "TRIPCOM",
            "chain": "",
            "free_cancellation": true,
            "special": false,
            "room_name": "Villa",
            "rooms": [
              {
                "name": "Villa",
                "flags": []
              }
            ],
            "offer_flags_new": {
              "breakfast": "Breakfast included",
              "refundable": "Free cancellation"
            },
            "partner_name": "Trip.com",
            "partner_logo": "https://hotelscan.com/apis/vendors/ctrp/logo.svg?pos=zz"
          },
          {
            "price": 802.21,
            "brt": "o2r#",
            "rf": "o2r#",
            "brf": 8421440,
            "rt": 8421440,
            "vendor": "agda",
            "vendor_id_raw": "41483",
            "mota_code": null,
            "direct_offer": false,
            "offer_flags": [],
            "jc_code": "",
            "chain": "",
            "free_cancellation": false,
            "special": false,
            "room_name": "Villa",
            "rooms": [
              {
                "name": "Villa",
                "flags": []
              }
            ],
            "offer_flags_new": [],
            "partner_name": "Agoda",
            "partner_logo": "https://hotelscan.com/apis/vendors/agda/logo.svg?pos=zz"
          },
          {
            "price": 802.82,
            "brt": "o2r#k",
            "rf": "o2r#k",
            "brf": 11075712,
            "rt": 11075712,
            "vendor": "ostr",
            "vendor_id_raw": "8120201",
            "mota_code": null,
            "direct_offer": false,
            "offer_flags": [
              "Free cancellation",
              "Pay at the property"
            ],
            "jc_code": "",
            "chain": "",
            "free_cancellation": true,
            "special": false,
            "room_name": "Villa - King bed",
            "rooms": [
              {
                "name": "Villa - King bed",
                "flags": [
                  "King bed"
                ]
              }
            ],
            "offer_flags_new": {
              "refundable": "Free cancellation",
              "pay_at_hotel": "Pay at the property"
            },
            "partner_name": "Zenhotels",
            "partner_logo": "https://hotelscan.com/apis/vendors/ostr/logo.svg?pos=zz"
          },
          {
            "price": 809.88,
            "brt": "o2r#",
            "rf": "o2r#",
            "brf": 9502848,
            "rt": 9502848,
            "vendor": "htls",
            "vendor_id_raw": "469335",
            "mota_code": null,
            "direct_offer": false,
            "offer_flags": [
              "Breakfast included",
              "Free cancellation",
              "Pay at the property"
            ],
            "jc_code": "",
            "chain": "",
            "free_cancellation": true,
            "special": false,
            "room_name": "Villa",
            "rooms": [
              {
                "name": "Villa",
                "flags": []
              }
            ],
            "offer_flags_new": {
              "breakfast": "Breakfast included",
              "refundable": "Free cancellation",
              "pay_at_hotel": "Pay at the property"
            },
            "partner_name": "Hotels.com",
            "partner_logo": "https://hotelscan.com/apis/vendors/htls/logo.svg?pos=zz"
          },
          {
            "price": 809.88,
            "brt": "o2r#",
            "rf": "o2r#",
            "brf": 9502848,
            "rt": 9502848,
            "vendor": "expd",
            "vendor_id_raw": "8751436",
            "mota_code": null,
            "direct_offer": false,
            "offer_flags": [
              "Breakfast included",
              "Free cancellation",
              "Pay at the property"
            ],
            "jc_code": "EXPEDIA",
            "chain": "",
            "free_cancellation": true,
            "special": false,
            "room_name": "Villa",
            "rooms": [
              {
                "name": "Villa",
                "flags": []
              }
            ],
            "offer_flags_new": {
              "breakfast": "Breakfast included",
              "refundable": "Free cancellation",
              "pay_at_hotel": "Pay at the property"
            },
            "partner_name": "Expedia",
            "partner_logo": "https://hotelscan.com/apis/vendors/expd/logo.svg?pos=zz"
          },
          {
            "price": 827.94,
            "brt": "o2r#",
            "rf": "o2r#",
            "brf": 9502784,
            "rt": 9502784,
            "vendor": "agda",
            "vendor_id_raw": "41483",
            "mota_code": null,
            "direct_offer": false,
            "offer_flags": [
              "Breakfast included",
              "Free cancellation"
            ],
            "jc_code": "",
            "chain": "",
            "free_cancellation": true,
            "special": false,
            "room_name": "Villa",
            "rooms": [
              {
                "name": "Villa",
                "flags": []
              }
            ],
            "offer_flags_new": {
              "breakfast": "Breakfast included",
              "refundable": "Free cancellation"
            },
            "partner_name": "Agoda",
            "partner_logo": "https://hotelscan.com/apis/vendors/agda/logo.svg?pos=zz"
          },
          {
            "price": 835.58,
            "brt": "o2r#",
            "rf": "o2r#",
            "brf": 11075648,
            "rt": 11075648,
            "vendor": "bkng",
            "vendor_id_raw": "568007",
            "mota_code": null,
            "direct_offer": false,
            "offer_flags": [
              "Free cancellation"
            ],
            "jc_code": "",
            "chain": "",
            "free_cancellation": true,
            "special": false,
            "room_name": "Villa",
            "rooms": [
              {
                "name": "Villa",
                "flags": []
              }
            ],
            "offer_flags_new": {
              "refundable": "Free cancellation"
            },
            "partner_name": "Booking.com",
            "partner_logo": "https://hotelscan.com/apis/vendors/bkng/logo.svg?pos=zz"
          },
          {
            "price": 868.13,
            "brt": "o2r#",
            "rf": "o2r#",
            "brf": 8421440,
            "rt": 8421440,
            "vendor": "agda",
            "vendor_id_raw": "41483",
            "mota_code": null,
            "direct_offer": false,
            "offer_flags": [],
            "jc_code": "",
            "chain": "",
            "free_cancellation": false,
            "special": false,
            "room_name": "Villa",
            "rooms": [
              {
                "name": "Villa",
                "flags": []
              }
            ],
            "offer_flags_new": [],
            "partner_name": "Agoda",
            "partner_logo": "https://hotelscan.com/apis/vendors/agda/logo.svg?pos=zz"
          },
          {
            "price": 883.63,
            "brt": "o2r#b",
            "rf": "o2r#b",
            "brf": 9470016,
            "rt": 9470016,
            "vendor": "stfl",
            "vendor_id_raw": "52202",
            "mota_code": null,
            "direct_offer": false,
            "offer_flags": [
              "Breakfast included"
            ],
            "jc_code": "",
            "chain": "",
            "free_cancellation": false,
            "special": false,
            "room_name": "Villa - Choice of single or double beds",
            "rooms": [
              {
                "name": "Villa - Choice of single or double beds",
                "flags": [
                  "Choice of single or double beds"
                ]
              }
            ],
            "offer_flags_new": {
              "breakfast": "Breakfast included"
            },
            "partner_name": "Stayforlong",
            "partner_logo": "https://hotelscan.com/apis/vendors/stfl/logo.svg?pos=zz"
          },
          {
            "price": 896.27,
            "brt": "o2r#",
            "rf": "o2r#",
            "brf": 9502784,
            "rt": 9502784,
            "vendor": "agda",
            "vendor_id_raw": "41483",
            "mota_code": null,
            "direct_offer": false,
            "offer_flags": [
              "Breakfast included",
              "Free cancellation"
            ],
            "jc_code": "",
            "chain": "",
            "free_cancellation": true,
            "special": false,
            "room_name": "Villa",
            "rooms": [
              {
                "name": "Villa",
                "flags": []
              }
            ],
            "offer_flags_new": {
              "breakfast": "Breakfast included",
              "refundable": "Free cancellation"
            },
            "partner_name": "Agoda",
            "partner_logo": "https://hotelscan.com/apis/vendors/agda/logo.svg?pos=zz"
          },
          {
            "price": 904.54,
            "brt": "o2r#",
            "rf": "o2r#",
            "brf": 11075648,
            "rt": 11075648,
            "vendor": "bkng",
            "vendor_id_raw": "568007",
            "mota_code": null,
            "direct_offer": false,
            "offer_flags": [
              "Free cancellation"
            ],
            "jc_code": "",
            "chain": "",
            "free_cancellation": true,
            "special": false,
            "room_name": "Villa",
            "rooms": [
              {
                "name": "Villa",
                "flags": []
              }
            ],
            "offer_flags_new": {
              "refundable": "Free cancellation"
            },
            "partner_name": "Booking.com",
            "partner_logo": "https://hotelscan.com/apis/vendors/bkng/logo.svg?pos=zz"
          },
          {
            "price": 943.46,
            "brt": "o2d#",
            "rf": "o2d#",
            "brf": 9502784,
            "rt": 9502784,
            "vendor": "agda",
            "vendor_id_raw": "41483",
            "mota_code": null,
            "direct_offer": false,
            "offer_flags": [
              "Breakfast included",
              "Free cancellation"
            ],
            "jc_code": "",
            "chain": "",
            "free_cancellation": true,
            "special": false,
            "room_name": "Deluxe villa",
            "rooms": [
              {
                "name": "Deluxe villa",
                "flags": []
              }
            ],
            "offer_flags_new": {
              "breakfast": "Breakfast included",
              "refundable": "Free cancellation"
            },
            "partner_name": "Agoda",
            "partner_logo": "https://hotelscan.com/apis/vendors/agda/logo.svg?pos=zz"
          },
          {
            "price": 950.02,
            "brt": "o2r#a",
            "rf": "o2r#a",
            "brf": 11042880,
            "rt": 11042880,
            "vendor": "ostr",
            "vendor_id_raw": "8120201",
            "mota_code": null,
            "direct_offer": false,
            "offer_flags": [],
            "jc_code": "",
            "chain": "",
            "free_cancellation": false,
            "special": false,
            "room_name": "Villa - Bed type subject to availability",
            "rooms": [
              {
                "name": "Villa - Bed type subject to availability",
                "flags": [
                  "Bed type subject to availability"
                ]
              }
            ],
            "offer_flags_new": [],
            "partner_name": "Zenhotels",
            "partner_logo": "https://hotelscan.com/apis/vendors/ostr/logo.svg?pos=zz"
          },
          {
            "price": 985.22,
            "brt": "o2r#a",
            "rf": "o2r#a",
            "brf": 11042880,
            "rt": 11042880,
            "vendor": "ostr",
            "vendor_id_raw": "8120201",
            "mota_code": null,
            "direct_offer": false,
            "offer_flags": [],
            "jc_code": "",
            "chain": "",
            "free_cancellation": false,
            "special": false,
            "room_name": "Villa - Bed type subject to availability",
            "rooms": [
              {
                "name": "Villa - Bed type subject to availability",
                "flags": [
                  "Bed type subject to availability"
                ]
              }
            ],
            "offer_flags_new": [],
            "partner_name": "Zenhotels",
            "partner_logo": "https://hotelscan.com/apis/vendors/ostr/logo.svg?pos=zz"
          },
          {
            "price": 1013.82,
            "brt": "o2r#d",
            "rf": "o2r#d",
            "brf": 11042880,
            "rt": 11042880,
            "vendor": "ostr",
            "vendor_id_raw": "8120201",
            "mota_code": null,
            "direct_offer": false,
            "offer_flags": [],
            "jc_code": "",
            "chain": "",
            "free_cancellation": false,
            "special": false,
            "room_name": "Villa - Double bed",
            "rooms": [
              {
                "name": "Villa - Double bed",
                "flags": [
                  "Double bed"
                ]
              }
            ],
            "offer_flags_new": [],
            "partner_name": "Zenhotels",
            "partner_logo": "https://hotelscan.com/apis/vendors/ostr/logo.svg?pos=zz"
          },
          {
            "price": 1017.22,
            "brt": "o2r#d",
            "rf": "o2r#d",
            "brf": 11042880,
            "rt": 11042880,
            "vendor": "ostr",
            "vendor_id_raw": "8120201",
            "mota_code": null,
            "direct_offer": false,
            "offer_flags": [],
            "jc_code": "",
            "chain": "",
            "free_cancellation": false,
            "special": false,
            "room_name": "Villa - Double bed",
            "rooms": [
              {
                "name": "Villa - Double bed",
                "flags": [
                  "Double bed"
                ]
              }
            ],
            "offer_flags_new": [],
            "partner_name": "Zenhotels",
            "partner_logo": "https://hotelscan.com/apis/vendors/ostr/logo.svg?pos=zz"
          },
          {
            "price": 1031.37,
            "brt": "e2r#",
            "rf": "e2r#",
            "brf": 9502784,
            "rt": 9502784,
            "vendor": "agda",
            "vendor_id_raw": "41483",
            "mota_code": null,
            "direct_offer": false,
            "offer_flags": [
              "Breakfast included",
              "Free cancellation"
            ],
            "jc_code": "",
            "chain": "",
            "free_cancellation": true,
            "special": false,
            "room_name": "Suite",
            "rooms": [
              {
                "name": "Suite",
                "flags": []
              }
            ],
            "offer_flags_new": {
              "breakfast": "Breakfast included",
              "refundable": "Free cancellation"
            },
            "partner_name": "Agoda",
            "partner_logo": "https://hotelscan.com/apis/vendors/agda/logo.svg?pos=zz"
          },
          {
            "price": 1042.58,
            "brt": "e2r#",
            "rf": "e2r#",
            "brf": 9502784,
            "rt": 9502784,
            "vendor": "agda",
            "vendor_id_raw": "41483",
            "mota_code": null,
            "direct_offer": false,
            "offer_flags": [
              "Breakfast included",
              "Free cancellation"
            ],
            "jc_code": "",
            "chain": "",
            "free_cancellation": true,
            "special": false,
            "room_name": "Suite",
            "rooms": [
              {
                "name": "Suite",
                "flags": []
              }
            ],
            "offer_flags_new": {
              "breakfast": "Breakfast included",
              "refundable": "Free cancellation"
            },
            "partner_name": "Agoda",
            "partner_logo": "https://hotelscan.com/apis/vendors/agda/logo.svg?pos=zz"
          },
          {
            "price": 1055.02,
            "brt": "o2r#a",
            "rf": "o2r#a",
            "brf": 11042880,
            "rt": 11042880,
            "vendor": "ostr",
            "vendor_id_raw": "8120201",
            "mota_code": null,
            "direct_offer": false,
            "offer_flags": [],
            "jc_code": "",
            "chain": "",
            "free_cancellation": false,
            "special": false,
            "room_name": "Villa - Bed type subject to availability",
            "rooms": [
              {
                "name": "Villa - Bed type subject to availability",
                "flags": [
                  "Bed type subject to availability"
                ]
              }
            ],
            "offer_flags_new": [],
            "partner_name": "Zenhotels",
            "partner_logo": "https://hotelscan.com/apis/vendors/ostr/logo.svg?pos=zz"
          },
          {
            "price": 1057.72,
            "brt": "o2d#k",
            "rf": "o2d#k",
            "brf": 11075648,
            "rt": 11075648,
            "vendor": "ostr",
            "vendor_id_raw": "8120201",
            "mota_code": null,
            "direct_offer": false,
            "offer_flags": [
              "Free cancellation"
            ],
            "jc_code": "",
            "chain": "",
            "free_cancellation": true,
            "special": false,
            "room_name": "Deluxe villa - King bed",
            "rooms": [
              {
                "name": "Deluxe villa - King bed",
                "flags": [
                  "King bed"
                ]
              }
            ],
            "offer_flags_new": {
              "refundable": "Free cancellation"
            },
            "partner_name": "Zenhotels",
            "partner_logo": "https://hotelscan.com/apis/vendors/ostr/logo.svg?pos=zz"
          },
          {
            "price": 1084.82,
            "brt": "o2r#d",
            "rf": "o2r#d",
            "brf": 11042880,
            "rt": 11042880,
            "vendor": "ostr",
            "vendor_id_raw": "8120201",
            "mota_code": null,
            "direct_offer": false,
            "offer_flags": [],
            "jc_code": "",
            "chain": "",
            "free_cancellation": false,
            "special": false,
            "room_name": "Villa - Double bed",
            "rooms": [
              {
                "name": "Villa - Double bed",
                "flags": [
                  "Double bed"
                ]
              }
            ],
            "offer_flags_new": [],
            "partner_name": "Zenhotels",
            "partner_logo": "https://hotelscan.com/apis/vendors/ostr/logo.svg?pos=zz"
          },
          {
            "price": 1156.26,
            "brt": "e2r#q",
            "rf": "e2r#q",
            "brf": 11075648,
            "rt": 11075648,
            "vendor": "ostr",
            "vendor_id_raw": "8120201",
            "mota_code": null,
            "direct_offer": false,
            "offer_flags": [
              "Free cancellation"
            ],
            "jc_code": "",
            "chain": "",
            "free_cancellation": true,
            "special": false,
            "room_name": "Suite - Queen bed",
            "rooms": [
              {
                "name": "Suite - Queen bed",
                "flags": [
                  "Queen bed"
                ]
              }
            ],
            "offer_flags_new": {
              "refundable": "Free cancellation"
            },
            "partner_name": "Zenhotels",
            "partner_logo": "https://hotelscan.com/apis/vendors/ostr/logo.svg?pos=zz"
          },
          {
            "price": 1160.22,
            "brt": "o2d#k",
            "rf": "o2d#k",
            "brf": 11075712,
            "rt": 11075712,
            "vendor": "ostr",
            "vendor_id_raw": "8120201",
            "mota_code": null,
            "direct_offer": false,
            "offer_flags": [
              "Free cancellation",
              "Pay at the property"
            ],
            "jc_code": "",
            "chain": "",
            "free_cancellation": true,
            "special": false,
            "room_name": "Deluxe villa - King bed",
            "rooms": [
              {
                "name": "Deluxe villa - King bed",
                "flags": [
                  "King bed"
                ]
              }
            ],
            "offer_flags_new": {
              "refundable": "Free cancellation",
              "pay_at_hotel": "Pay at the property"
            },
            "partner_name": "Zenhotels",
            "partner_logo": "https://hotelscan.com/apis/vendors/ostr/logo.svg?pos=zz"
          },
          {
            "price": 1170.53,
            "brt": "o2d#",
            "rf": "o2d#",
            "brf": 9502848,
            "rt": 9502848,
            "vendor": "htls",
            "vendor_id_raw": "469335",
            "mota_code": null,
            "direct_offer": false,
            "offer_flags": [
              "Breakfast included",
              "Free cancellation",
              "Pay at the property"
            ],
            "jc_code": "",
            "chain": "",
            "free_cancellation": true,
            "special": false,
            "room_name": "Deluxe villa",
            "rooms": [
              {
                "name": "Deluxe villa",
                "flags": []
              }
            ],
            "offer_flags_new": {
              "breakfast": "Breakfast included",
              "refundable": "Free cancellation",
              "pay_at_hotel": "Pay at the property"
            },
            "partner_name": "Hotels.com",
            "partner_logo": "https://hotelscan.com/apis/vendors/htls/logo.svg?pos=zz"
          },
          {
            "price": 1170.53,
            "brt": "o2d#",
            "rf": "o2d#",
            "brf": 9502848,
            "rt": 9502848,
            "vendor": "expd",
            "vendor_id_raw": "8751436",
            "mota_code": null,
            "direct_offer": false,
            "offer_flags": [
              "Breakfast included",
              "Free cancellation",
              "Pay at the property"
            ],
            "jc_code": "EXPEDIA",
            "chain": "",
            "free_cancellation": true,
            "special": false,
            "room_name": "Deluxe villa",
            "rooms": [
              {
                "name": "Deluxe villa",
                "flags": []
              }
            ],
            "offer_flags_new": {
              "breakfast": "Breakfast included",
              "refundable": "Free cancellation",
              "pay_at_hotel": "Pay at the property"
            },
            "partner_name": "Expedia",
            "partner_logo": "https://hotelscan.com/apis/vendors/expd/logo.svg?pos=zz"
          },
          {
            "price": 1268.42,
            "brt": "e2r#q",
            "rf": "e2r#q",
            "brf": 11075712,
            "rt": 11075712,
            "vendor": "ostr",
            "vendor_id_raw": "8120201",
            "mota_code": null,
            "direct_offer": false,
            "offer_flags": [
              "Free cancellation",
              "Pay at the property"
            ],
            "jc_code": "",
            "chain": "",
            "free_cancellation": true,
            "special": false,
            "room_name": "Suite - Queen bed",
            "rooms": [
              {
                "name": "Suite - Queen bed",
                "flags": [
                  "Queen bed"
                ]
              }
            ],
            "offer_flags_new": {
              "refundable": "Free cancellation",
              "pay_at_hotel": "Pay at the property"
            },
            "partner_name": "Zenhotels",
            "partner_logo": "https://hotelscan.com/apis/vendors/ostr/logo.svg?pos=zz"
          },
          {
            "price": 1279.75,
            "brt": "e2r#",
            "rf": "e2r#",
            "brf": 9502784,
            "rt": 9502784,
            "vendor": "htls",
            "vendor_id_raw": "469335",
            "mota_code": null,
            "direct_offer": false,
            "offer_flags": [
              "Breakfast included",
              "Free cancellation"
            ],
            "jc_code": "",
            "chain": "",
            "free_cancellation": true,
            "special": false,
            "room_name": "Suite",
            "rooms": [
              {
                "name": "Suite",
                "flags": []
              }
            ],
            "offer_flags_new": {
              "breakfast": "Breakfast included",
              "refundable": "Free cancellation"
            },
            "partner_name": "Hotels.com",
            "partner_logo": "https://hotelscan.com/apis/vendors/htls/logo.svg?pos=zz"
          },
          {
            "price": 1279.75,
            "brt": "e2r#",
            "rf": "e2r#",
            "brf": 9502784,
            "rt": 9502784,
            "vendor": "expd",
            "vendor_id_raw": "8751436",
            "mota_code": null,
            "direct_offer": false,
            "offer_flags": [
              "Breakfast included",
              "Free cancellation"
            ],
            "jc_code": "EXPEDIA",
            "chain": "",
            "free_cancellation": true,
            "special": false,
            "room_name": "Suite",
            "rooms": [
              {
                "name": "Suite",
                "flags": []
              }
            ],
            "offer_flags_new": {
              "breakfast": "Breakfast included",
              "refundable": "Free cancellation"
            },
            "partner_name": "Expedia",
            "partner_logo": "https://hotelscan.com/apis/vendors/expd/logo.svg?pos=zz"
          },
          {
            "price": 1279.76,
            "brt": "e2r#",
            "rf": "e2r#",
            "brf": 9502848,
            "rt": 9502848,
            "vendor": "htls",
            "vendor_id_raw": "469335",
            "mota_code": null,
            "direct_offer": false,
            "offer_flags": [
              "Breakfast included",
              "Free cancellation",
              "Pay at the property"
            ],
            "jc_code": "",
            "chain": "",
            "free_cancellation": true,
            "special": false,
            "room_name": "Suite",
            "rooms": [
              {
                "name": "Suite",
                "flags": []
              }
            ],
            "offer_flags_new": {
              "breakfast": "Breakfast included",
              "refundable": "Free cancellation",
              "pay_at_hotel": "Pay at the property"
            },
            "partner_name": "Hotels.com",
            "partner_logo": "https://hotelscan.com/apis/vendors/htls/logo.svg?pos=zz"
          },
          {
            "price": 1279.76,
            "brt": "e2r#",
            "rf": "e2r#",
            "brf": 9502848,
            "rt": 9502848,
            "vendor": "expd",
            "vendor_id_raw": "8751436",
            "mota_code": null,
            "direct_offer": false,
            "offer_flags": [
              "Breakfast included",
              "Free cancellation",
              "Pay at the property"
            ],
            "jc_code": "EXPEDIA",
            "chain": "",
            "free_cancellation": true,
            "special": false,
            "room_name": "Suite",
            "rooms": [
              {
                "name": "Suite",
                "flags": []
              }
            ],
            "offer_flags_new": {
              "breakfast": "Breakfast included",
              "refundable": "Free cancellation",
              "pay_at_hotel": "Pay at the property"
            },
            "partner_name": "Expedia",
            "partner_logo": "https://hotelscan.com/apis/vendors/expd/logo.svg?pos=zz"
          },
          {
            "price": 1296.47,
            "brt": "o2d#",
            "rf": "o2d#",
            "brf": 9502784,
            "rt": 9502784,
            "vendor": "agda",
            "vendor_id_raw": "41483",
            "mota_code": null,
            "direct_offer": false,
            "offer_flags": [
              "Breakfast included",
              "Free cancellation"
            ],
            "jc_code": "",
            "chain": "",
            "free_cancellation": true,
            "special": false,
            "room_name": "Deluxe villa",
            "rooms": [
              {
                "name": "Deluxe villa",
                "flags": []
              }
            ],
            "offer_flags_new": {
              "breakfast": "Breakfast included",
              "refundable": "Free cancellation"
            },
            "partner_name": "Agoda",
            "partner_logo": "https://hotelscan.com/apis/vendors/agda/logo.svg?pos=zz"
          },
          {
            "price": 1308.44,
            "brt": "o2d#",
            "rf": "o2d#",
            "brf": 11075648,
            "rt": 11075648,
            "vendor": "bkng",
            "vendor_id_raw": "568007",
            "mota_code": null,
            "direct_offer": false,
            "offer_flags": [
              "Free cancellation"
            ],
            "jc_code": "",
            "chain": "",
            "free_cancellation": true,
            "special": false,
            "room_name": "Deluxe villa",
            "rooms": [
              {
                "name": "Deluxe villa",
                "flags": []
              }
            ],
            "offer_flags_new": {
              "refundable": "Free cancellation"
            },
            "partner_name": "Booking.com",
            "partner_logo": "https://hotelscan.com/apis/vendors/bkng/logo.svg?pos=zz"
          },
          {
            "price": 1430.76,
            "brt": "e2r#",
            "rf": "e2r#",
            "brf": 11075648,
            "rt": 11075648,
            "vendor": "bkng",
            "vendor_id_raw": "568007",
            "mota_code": null,
            "direct_offer": false,
            "offer_flags": [
              "Free cancellation"
            ],
            "jc_code": "",
            "chain": "",
            "free_cancellation": true,
            "special": false,
            "room_name": "Suite",
            "rooms": [
              {
                "name": "Suite",
                "flags": []
              }
            ],
            "offer_flags_new": {
              "refundable": "Free cancellation"
            },
            "partner_name": "Booking.com",
            "partner_logo": "https://hotelscan.com/apis/vendors/bkng/logo.svg?pos=zz"
          },
          {
            "price": 1446.35,
            "brt": "e2r#",
            "rf": "e2r#",
            "brf": 11075648,
            "rt": 11075648,
            "vendor": "bkng",
            "vendor_id_raw": "568007",
            "mota_code": null,
            "direct_offer": false,
            "offer_flags": [
              "Free cancellation"
            ],
            "jc_code": "",
            "chain": "",
            "free_cancellation": true,
            "special": false,
            "room_name": "Suite",
            "rooms": [
              {
                "name": "Suite",
                "flags": []
              }
            ],
            "offer_flags_new": {
              "refundable": "Free cancellation"
            },
            "partner_name": "Booking.com",
            "partner_logo": "https://hotelscan.com/apis/vendors/bkng/logo.svg?pos=zz"
          },
          {
            "price": 1451.28,
            "brt": "o2r#",
            "rf": "o2r#",
            "brf": 11075648,
            "rt": 11075648,
            "vendor": "bkng",
            "vendor_id_raw": "568007",
            "mota_code": null,
            "direct_offer": false,
            "offer_flags": [
              "Free cancellation"
            ],
            "jc_code": "",
            "chain": "",
            "free_cancellation": true,
            "special": false,
            "room_name": "Villa",
            "rooms": [
              {
                "name": "Villa",
                "flags": []
              }
            ],
            "offer_flags_new": {
              "refundable": "Free cancellation"
            },
            "partner_name": "Booking.com",
            "partner_logo": "https://hotelscan.com/apis/vendors/bkng/logo.svg?pos=zz"
          },
          {
            "price": 1469.62,
            "brt": "o2r#d",
            "rf": "o2r#d",
            "brf": 11042880,
            "rt": 11042880,
            "vendor": "ostr",
            "vendor_id_raw": "8120201",
            "mota_code": null,
            "direct_offer": false,
            "offer_flags": [],
            "jc_code": "",
            "chain": "",
            "free_cancellation": false,
            "special": false,
            "room_name": "Villa - Double bed",
            "rooms": [
              {
                "name": "Villa - Double bed",
                "flags": [
                  "Double bed"
                ]
              }
            ],
            "offer_flags_new": [],
            "partner_name": "Zenhotels",
            "partner_logo": "https://hotelscan.com/apis/vendors/ostr/logo.svg?pos=zz"
          },
          {
            "price": 1499.44,
            "brt": "p2r#d",
            "rf": "p2r#d",
            "brf": 11075648,
            "rt": 11075648,
            "vendor": "ostr",
            "vendor_id_raw": "8120201",
            "mota_code": null,
            "direct_offer": false,
            "offer_flags": [
              "Free cancellation"
            ],
            "jc_code": "",
            "chain": "",
            "free_cancellation": true,
            "special": false,
            "room_name": "Standard room - Double bed",
            "rooms": [
              {
                "name": "Standard room - Double bed",
                "flags": [
                  "Double bed"
                ]
              }
            ],
            "offer_flags_new": {
              "refundable": "Free cancellation"
            },
            "partner_name": "Zenhotels",
            "partner_logo": "https://hotelscan.com/apis/vendors/ostr/logo.svg?pos=zz"
          },
          {
            "price": 1500.72,
            "brt": "o2r#d",
            "rf": "o2r#d",
            "brf": 11042880,
            "rt": 11042880,
            "vendor": "ostr",
            "vendor_id_raw": "8120201",
            "mota_code": null,
            "direct_offer": false,
            "offer_flags": [],
            "jc_code": "",
            "chain": "",
            "free_cancellation": false,
            "special": false,
            "room_name": "Villa - Double bed",
            "rooms": [
              {
                "name": "Villa - Double bed",
                "flags": [
                  "Double bed"
                ]
              }
            ],
            "offer_flags_new": [],
            "partner_name": "Zenhotels",
            "partner_logo": "https://hotelscan.com/apis/vendors/ostr/logo.svg?pos=zz"
          },
          {
            "price": 1520.24,
            "brt": "o2r#",
            "rf": "o2r#",
            "brf": 11075648,
            "rt": 11075648,
            "vendor": "bkng",
            "vendor_id_raw": "568007",
            "mota_code": null,
            "direct_offer": false,
            "offer_flags": [
              "Free cancellation"
            ],
            "jc_code": "",
            "chain": "",
            "free_cancellation": true,
            "special": false,
            "room_name": "Villa",
            "rooms": [
              {
                "name": "Villa",
                "flags": []
              }
            ],
            "offer_flags_new": {
              "refundable": "Free cancellation"
            },
            "partner_name": "Booking.com",
            "partner_logo": "https://hotelscan.com/apis/vendors/bkng/logo.svg?pos=zz"
          },
          {
            "price": 1522.82,
            "brt": "e2r#d",
            "rf": "e2r#d",
            "brf": 11042880,
            "rt": 11042880,
            "vendor": "ostr",
            "vendor_id_raw": "8120201",
            "mota_code": null,
            "direct_offer": false,
            "offer_flags": [],
            "jc_code": "",
            "chain": "",
            "free_cancellation": false,
            "special": false,
            "room_name": "Suite - Double bed",
            "rooms": [
              {
                "name": "Suite - Double bed",
                "flags": [
                  "Double bed"
                ]
              }
            ],
            "offer_flags_new": [],
            "partner_name": "Zenhotels",
            "partner_logo": "https://hotelscan.com/apis/vendors/ostr/logo.svg?pos=zz"
          },
          {
            "price": 1587.42,
            "brt": "e2r#d",
            "rf": "e2r#d",
            "brf": 11042880,
            "rt": 11042880,
            "vendor": "ostr",
            "vendor_id_raw": "8120201",
            "mota_code": null,
            "direct_offer": false,
            "offer_flags": [],
            "jc_code": "",
            "chain": "",
            "free_cancellation": false,
            "special": false,
            "room_name": "Suite - Double bed",
            "rooms": [
              {
                "name": "Suite - Double bed",
                "flags": [
                  "Double bed"
                ]
              }
            ],
            "offer_flags_new": [],
            "partner_name": "Zenhotels",
            "partner_logo": "https://hotelscan.com/apis/vendors/ostr/logo.svg?pos=zz"
          },
          {
            "price": 1603.02,
            "brt": "e2r#d",
            "rf": "e2r#d",
            "brf": 11042880,
            "rt": 11042880,
            "vendor": "ostr",
            "vendor_id_raw": "8120201",
            "mota_code": null,
            "direct_offer": false,
            "offer_flags": [],
            "jc_code": "",
            "chain": "",
            "free_cancellation": false,
            "special": false,
            "room_name": "Suite - Double bed",
            "rooms": [
              {
                "name": "Suite - Double bed",
                "flags": [
                  "Double bed"
                ]
              }
            ],
            "offer_flags_new": [],
            "partner_name": "Zenhotels",
            "partner_logo": "https://hotelscan.com/apis/vendors/ostr/logo.svg?pos=zz"
          },
          {
            "price": 1613.49,
            "brt": "e2r#q",
            "rf": "e2r#q",
            "brf": 11075648,
            "rt": 11075648,
            "vendor": "ostr",
            "vendor_id_raw": "8120201",
            "mota_code": null,
            "direct_offer": false,
            "offer_flags": [
              "Free cancellation"
            ],
            "jc_code": "",
            "chain": "",
            "free_cancellation": true,
            "special": false,
            "room_name": "Suite - Queen bed",
            "rooms": [
              {
                "name": "Suite - Queen bed",
                "flags": [
                  "Queen bed"
                ]
              }
            ],
            "offer_flags_new": {
              "refundable": "Free cancellation"
            },
            "partner_name": "Zenhotels",
            "partner_logo": "https://hotelscan.com/apis/vendors/ostr/logo.svg?pos=zz"
          },
          {
            "price": 1634.12,
            "brt": "e2r#d",
            "rf": "e2r#d",
            "brf": 11042880,
            "rt": 11042880,
            "vendor": "ostr",
            "vendor_id_raw": "8120201",
            "mota_code": null,
            "direct_offer": false,
            "offer_flags": [],
            "jc_code": "",
            "chain": "",
            "free_cancellation": false,
            "special": false,
            "room_name": "Suite - Double bed",
            "rooms": [
              {
                "name": "Suite - Double bed",
                "flags": [
                  "Double bed"
                ]
              }
            ],
            "offer_flags_new": [],
            "partner_name": "Zenhotels",
            "partner_logo": "https://hotelscan.com/apis/vendors/ostr/logo.svg?pos=zz"
          },
          {
            "price": 1645.62,
            "brt": "p2r#d",
            "rf": "p2r#d",
            "brf": 11075712,
            "rt": 11075712,
            "vendor": "ostr",
            "vendor_id_raw": "8120201",
            "mota_code": null,
            "direct_offer": false,
            "offer_flags": [
              "Free cancellation",
              "Pay at the property"
            ],
            "jc_code": "",
            "chain": "",
            "free_cancellation": true,
            "special": false,
            "room_name": "Standard room - Double bed",
            "rooms": [
              {
                "name": "Standard room - Double bed",
                "flags": [
                  "Double bed"
                ]
              }
            ],
            "offer_flags_new": {
              "refundable": "Free cancellation",
              "pay_at_hotel": "Pay at the property"
            },
            "partner_name": "Zenhotels",
            "partner_logo": "https://hotelscan.com/apis/vendors/ostr/logo.svg?pos=zz"
          },
          {
            "price": 1660.19,
            "brt": "z2r#",
            "rf": "z2r#",
            "brf": 9502848,
            "rt": 9502848,
            "vendor": "htls",
            "vendor_id_raw": "469335",
            "mota_code": null,
            "direct_offer": false,
            "offer_flags": [
              "Breakfast included",
              "Free cancellation",
              "Pay at the property"
            ],
            "jc_code": "",
            "chain": "",
            "free_cancellation": true,
            "special": false,
            "room_name": "Go to the booking site for more details",
            "rooms": [
              {
                "name": "Go to the booking site for more details",
                "flags": []
              }
            ],
            "offer_flags_new": {
              "breakfast": "Breakfast included",
              "refundable": "Free cancellation",
              "pay_at_hotel": "Pay at the property"
            },
            "partner_name": "Hotels.com",
            "partner_logo": "https://hotelscan.com/apis/vendors/htls/logo.svg?pos=zz"
          },
          {
            "price": 1660.19,
            "brt": "z2r#",
            "rf": "z2r#",
            "brf": 9502848,
            "rt": 9502848,
            "vendor": "expd",
            "vendor_id_raw": "8751436",
            "mota_code": null,
            "direct_offer": false,
            "offer_flags": [
              "Breakfast included",
              "Free cancellation",
              "Pay at the property"
            ],
            "jc_code": "EXPEDIA",
            "chain": "",
            "free_cancellation": true,
            "special": false,
            "room_name": "Go to the booking site for more details",
            "rooms": [
              {
                "name": "Go to the booking site for more details",
                "flags": []
              }
            ],
            "offer_flags_new": {
              "breakfast": "Breakfast included",
              "refundable": "Free cancellation",
              "pay_at_hotel": "Pay at the property"
            },
            "partner_name": "Expedia",
            "partner_logo": "https://hotelscan.com/apis/vendors/expd/logo.svg?pos=zz"
          },
          {
            "price": 1727.02,
            "brt": "e2r#q",
            "rf": "e2r#q",
            "brf": 11075712,
            "rt": 11075712,
            "vendor": "ostr",
            "vendor_id_raw": "8120201",
            "mota_code": null,
            "direct_offer": false,
            "offer_flags": [
              "Free cancellation",
              "Pay at the property"
            ],
            "jc_code": "",
            "chain": "",
            "free_cancellation": true,
            "special": false,
            "room_name": "Suite - Queen bed",
            "rooms": [
              {
                "name": "Suite - Queen bed",
                "flags": [
                  "Queen bed"
                ]
              }
            ],
            "offer_flags_new": {
              "refundable": "Free cancellation",
              "pay_at_hotel": "Pay at the property"
            },
            "partner_name": "Zenhotels",
            "partner_logo": "https://hotelscan.com/apis/vendors/ostr/logo.svg?pos=zz"
          },
          {
            "price": 1742.24,
            "brt": "e2r#",
            "rf": "e2r#",
            "brf": 9502784,
            "rt": 9502784,
            "vendor": "htls",
            "vendor_id_raw": "469335",
            "mota_code": null,
            "direct_offer": false,
            "offer_flags": [
              "Breakfast included",
              "Free cancellation"
            ],
            "jc_code": "",
            "chain": "",
            "free_cancellation": true,
            "special": false,
            "room_name": "Suite",
            "rooms": [
              {
                "name": "Suite",
                "flags": []
              }
            ],
            "offer_flags_new": {
              "breakfast": "Breakfast included",
              "refundable": "Free cancellation"
            },
            "partner_name": "Hotels.com",
            "partner_logo": "https://hotelscan.com/apis/vendors/htls/logo.svg?pos=zz"
          },
          {
            "price": 1742.24,
            "brt": "e2r#",
            "rf": "e2r#",
            "brf": 9502784,
            "rt": 9502784,
            "vendor": "expd",
            "vendor_id_raw": "8751436",
            "mota_code": null,
            "direct_offer": false,
            "offer_flags": [
              "Breakfast included",
              "Free cancellation"
            ],
            "jc_code": "EXPEDIA",
            "chain": "",
            "free_cancellation": true,
            "special": false,
            "room_name": "Suite",
            "rooms": [
              {
                "name": "Suite",
                "flags": []
              }
            ],
            "offer_flags_new": {
              "breakfast": "Breakfast included",
              "refundable": "Free cancellation"
            },
            "partner_name": "Expedia",
            "partner_logo": "https://hotelscan.com/apis/vendors/expd/logo.svg?pos=zz"
          },
          {
            "price": 1742.25,
            "brt": "e2r#",
            "rf": "e2r#",
            "brf": 9502848,
            "rt": 9502848,
            "vendor": "htls",
            "vendor_id_raw": "469335",
            "mota_code": null,
            "direct_offer": false,
            "offer_flags": [
              "Breakfast included",
              "Free cancellation",
              "Pay at the property"
            ],
            "jc_code": "",
            "chain": "",
            "free_cancellation": true,
            "special": false,
            "room_name": "Suite",
            "rooms": [
              {
                "name": "Suite",
                "flags": []
              }
            ],
            "offer_flags_new": {
              "breakfast": "Breakfast included",
              "refundable": "Free cancellation",
              "pay_at_hotel": "Pay at the property"
            },
            "partner_name": "Hotels.com",
            "partner_logo": "https://hotelscan.com/apis/vendors/htls/logo.svg?pos=zz"
          },
          {
            "price": 1742.25,
            "brt": "e2r#",
            "rf": "e2r#",
            "brf": 9502848,
            "rt": 9502848,
            "vendor": "expd",
            "vendor_id_raw": "8751436",
            "mota_code": null,
            "direct_offer": false,
            "offer_flags": [
              "Breakfast included",
              "Free cancellation",
              "Pay at the property"
            ],
            "jc_code": "EXPEDIA",
            "chain": "",
            "free_cancellation": true,
            "special": false,
            "room_name": "Suite",
            "rooms": [
              {
                "name": "Suite",
                "flags": []
              }
            ],
            "offer_flags_new": {
              "breakfast": "Breakfast included",
              "refundable": "Free cancellation",
              "pay_at_hotel": "Pay at the property"
            },
            "partner_name": "Expedia",
            "partner_logo": "https://hotelscan.com/apis/vendors/expd/logo.svg?pos=zz"
          },
          {
            "price": 1856.82,
            "brt": "z2r#",
            "rf": "z2r#",
            "brf": 11075648,
            "rt": 11075648,
            "vendor": "bkng",
            "vendor_id_raw": "568007",
            "mota_code": null,
            "direct_offer": false,
            "offer_flags": [
              "Free cancellation"
            ],
            "jc_code": "",
            "chain": "",
            "free_cancellation": true,
            "special": false,
            "room_name": "Go to the booking site for more details",
            "rooms": [
              {
                "name": "Go to the booking site for more details",
                "flags": []
              }
            ],
            "offer_flags_new": {
              "refundable": "Free cancellation"
            },
            "partner_name": "Booking.com",
            "partner_logo": "https://hotelscan.com/apis/vendors/bkng/logo.svg?pos=zz"
          },
          {
            "price": 1924.14,
            "brt": "o2d#",
            "rf": "o2d#",
            "brf": 11075648,
            "rt": 11075648,
            "vendor": "bkng",
            "vendor_id_raw": "568007",
            "mota_code": null,
            "direct_offer": false,
            "offer_flags": [
              "Free cancellation"
            ],
            "jc_code": "",
            "chain": "",
            "free_cancellation": true,
            "special": false,
            "room_name": "Deluxe villa",
            "rooms": [
              {
                "name": "Deluxe villa",
                "flags": []
              }
            ],
            "offer_flags_new": {
              "refundable": "Free cancellation"
            },
            "partner_name": "Booking.com",
            "partner_logo": "https://hotelscan.com/apis/vendors/bkng/logo.svg?pos=zz"
          },
          {
            "price": 1998.82,
            "brt": "p2r#d",
            "rf": "p2r#d",
            "brf": 11042880,
            "rt": 11042880,
            "vendor": "ostr",
            "vendor_id_raw": "8120201",
            "mota_code": null,
            "direct_offer": false,
            "offer_flags": [],
            "jc_code": "",
            "chain": "",
            "free_cancellation": false,
            "special": false,
            "room_name": "Standard room - Double bed",
            "rooms": [
              {
                "name": "Standard room - Double bed",
                "flags": [
                  "Double bed"
                ]
              }
            ],
            "offer_flags_new": [],
            "partner_name": "Zenhotels",
            "partner_logo": "https://hotelscan.com/apis/vendors/ostr/logo.svg?pos=zz"
          },
          {
            "price": 2046.45,
            "brt": "e2r#",
            "rf": "e2r#",
            "brf": 11075648,
            "rt": 11075648,
            "vendor": "bkng",
            "vendor_id_raw": "568007",
            "mota_code": null,
            "direct_offer": false,
            "offer_flags": [
              "Free cancellation"
            ],
            "jc_code": "",
            "chain": "",
            "free_cancellation": true,
            "special": false,
            "room_name": "Suite",
            "rooms": [
              {
                "name": "Suite",
                "flags": []
              }
            ],
            "offer_flags_new": {
              "refundable": "Free cancellation"
            },
            "partner_name": "Booking.com",
            "partner_logo": "https://hotelscan.com/apis/vendors/bkng/logo.svg?pos=zz"
          },
          {
            "price": 2062.05,
            "brt": "e2r#",
            "rf": "e2r#",
            "brf": 11075648,
            "rt": 11075648,
            "vendor": "bkng",
            "vendor_id_raw": "568007",
            "mota_code": null,
            "direct_offer": false,
            "offer_flags": [
              "Free cancellation"
            ],
            "jc_code": "",
            "chain": "",
            "free_cancellation": true,
            "special": false,
            "room_name": "Suite",
            "rooms": [
              {
                "name": "Suite",
                "flags": []
              }
            ],
            "offer_flags_new": {
              "refundable": "Free cancellation"
            },
            "partner_name": "Booking.com",
            "partner_logo": "https://hotelscan.com/apis/vendors/bkng/logo.svg?pos=zz"
          },
          {
            "price": 2472.52,
            "brt": "z2r#",
            "rf": "z2r#",
            "brf": 11075648,
            "rt": 11075648,
            "vendor": "bkng",
            "vendor_id_raw": "568007",
            "mota_code": null,
            "direct_offer": false,
            "offer_flags": [
              "Free cancellation"
            ],
            "jc_code": "",
            "chain": "",
            "free_cancellation": true,
            "special": false,
            "room_name": "Go to the booking site for more details",
            "rooms": [
              {
                "name": "Go to the booking site for more details",
                "flags": []
              }
            ],
            "offer_flags_new": {
              "refundable": "Free cancellation"
            },
            "partner_name": "Booking.com",
            "partner_logo": "https://hotelscan.com/apis/vendors/bkng/logo.svg?pos=zz"
          }
        ],
        "descriptions_language": {
          "general": {
            "original_language": true,
            "text": "Lily Beach Resort & Spa at Huvahendhoo as a Luxury 'Platinum Plan' Resort is approximately 25 minutes flying from the Male’ International Airport. *Price shown does NOT include arrival and return transfer, but is compulsory to book online Sunhotels POS,together with the hotel reservation. You are required to book the appropriate transfer and supply all the required transfer information. Hotel booking is not regarded as confirmed until the transfer booking has been completed. The all-new Lily Beach Resort & Spa officially opened on the 28th of March 2009. The Hotel whit Platinum Plan offers: gym, water sports centre equipped with non-motorized activities and motorized sports such as fun-tube rides and exhilarating banana-boat rides, a flood-lit tennis court, table tennis, darts, billiards/pool, beach volleyball. Big game fishing, sunrise fishing, or on a snorkeling safari. In the Evening: Live music, traditional local music, group games, discos, night fishing, traditional cultural variety shows, and various beach games. Deluxe Water Villas (36 Villas) : Villa Size 126m², with a distance of 15-feet between each villa, these villas are aesthetically appointed with a single piece hand-crafted standalone bathtub with Jacuzzi and an additional 7 sq.mts Jacuzzi pool on the deck offering a fantastic view of the entire lagoon accessible by your private stairs. A combination of natural wood and white marble flooring, a 4 poster king-sized bed, an over-sized day bed, and 42” LCD flat screen. In case of choosing the option of \"all inclusive\": The All Inclusive-concept includes all meals (breakfast, lunch, dinner and snacks) and mealtime drinks such as soft drinks, beer, wine, water and alcoholic drinks, all of local brands. Drinks are served from morning until late evening (approx until 22.-24.00 hrs). Opening times vary between different hotels. In certain hotels the activities program is also included. Children 0-2 yrs pay aprox. 8 USD directly at the resorts. You are requested to indicate the estimated arrival time and flight number while making the booking. Address: at Huvahendhoo South-East Ari Atoll Maldives Note: Transfer has to be booked at the same time as the Hotel"
          },
          "direction": {
            "original_language": true,
            "text": "Located in Huvahendhoo, Lily Beach Resort & Spa - All Inclusive is on a private beach. Villingilivaru Island Pier and Dhangethi Port are worth checking out if an activity is on the agenda, while those wishing to experience the area's natural beauty can explore Ari Atoll and Bunbaru Public Beach. Take an opportunity to explore the area for water adventures such as windsurfing and other activities like whale-watching."
          }
        },
        "chain_code": null,
        "bids": {
          "bkng": "j23",
          "agda": "j23",
          "stfl": "j23",
          "expd": "j23",
          "htls": "j23",
          "ostr": "j23",
          "ctrp": "j23"
        },
        "worst_offer": 883.63,
        "best_offer": 603.6,
        "best_offer_ota": "agda",
        "best_offer_mota": null,
        "discount": 30,
        "offers_count": 66,
        "coordinates": {
          "lat": 3.65285,
          "lng": 72.9537
        },
        "distance": 0.52,
        "neighborhood": null,
        "badge": null,
        "distances": [
          {
            "from": "center",
            "distance": 0.52,
            "time": 722,
            "means": "foot",
            "means_type": "foot"
          }
        ],
        "specs": {
          "bathrooms": null,
          "beds": null,
          "bedrooms": null,
          "guests": null,
          "square_meters": null
        },
        "toa_label": "resort",
        "top_amenities": [
          "indoor_pool",
          "outdoor_pool",
          "internet",
          "restaurant",
          "room_service"
        ],
        "transportations": {
          "airports": [],
          "trains": []
        },
        "images": [
          {
            "image_id": "685884221",
            "label": ""
          },
          {
            "image_id": "685884233",
            "label": ""
          },
          {
            "image_id": "685884196",
            "label": ""
          },
          {
            "image_id": "685884205",
            "label": ""
          },
          {
            "image_id": "685884185",
            "label": ""
          },
          {
            "image_id": "685884240",
            "label": ""
          },
          {
            "image_id": "685884204",
            "label": ""
          },
          {
            "image_id": "685884202",
            "label": ""
          },
          {
            "image_id": "685884214",
            "label": ""
          },
          {
            "image_id": "685884226",
            "label": ""
          },
          {
            "image_id": "685884208",
            "label": ""
          },
          {
            "image_id": "685884210",
            "label": ""
          },
          {
            "image_id": "685884236",
            "label": ""
          },
          {
            "image_id": "685884190",
            "label": ""
          },
          {
            "image_id": "685884197",
            "label": ""
          }
        ],
        "hero_offer": {
          "price": 603.6,
          "brt": "o2r#",
          "rf": "o2r#",
          "brf": 9502784,
          "rt": 9502784,
          "vendor": "agda",
          "vendor_id_raw": "41483",
          "mota_code": null,
          "direct_offer": false,
          "offer_flags": {
            "breakfast": "Breakfast included",
            "refundable": "Free cancellation"
          },
          "jc_code": "",
          "ranking_index": 0.96,
          "chain": "",
          "free_cancellation": true,
          "special": false,
          "room_name": "Villa",
          "rooms": [
            {
              "name": "Villa",
              "flags": []
            }
          ],
          "partner_name": "Agoda",
          "partner_logo": "https://hotelscan.com/apis/vendors/agda/logo.svg?pos=zz"
        },
        "rank": 0,
        "ctrl_srt": "im a ctrl teapot",
        "test_srt": "im a test teapot"
      }
    ],
    "filters": [],
    "query": {
      "pos": "zz"
    }
  }
}